keystone/__init__.py
keystone/exception.py
keystone/i18n.py
keystone/notifications.py
keystone/version.py
keystone/api/__init__.py
keystone/api/auth.py
keystone/api/credentials.py
keystone/api/discovery.py
keystone/api/domains.py
keystone/api/ec2tokens.py
keystone/api/endpoints.py
keystone/api/groups.py
keystone/api/limits.py
keystone/api/os_ep_filter.py
keystone/api/os_federation.py
keystone/api/os_inherit.py
keystone/api/os_oauth1.py
keystone/api/os_oauth2.py
keystone/api/os_revoke.py
keystone/api/os_simple_cert.py
keystone/api/policy.py
keystone/api/projects.py
keystone/api/regions.py
keystone/api/registered_limits.py
keystone/api/role_assignments.py
keystone/api/role_inferences.py
keystone/api/roles.py
keystone/api/s3tokens.py
keystone/api/services.py
keystone/api/system.py
keystone/api/trusts.py
keystone/api/users.py
keystone/api/_shared/EC2_S3_Resource.py
keystone/api/_shared/__init__.py
keystone/api/_shared/authentication.py
keystone/api/_shared/implied_roles.py
keystone/api/_shared/json_home_relations.py
keystone/api/_shared/saml.py
keystone/api/validation/__init__.py
keystone/api/validation/parameter_types.py
keystone/api/validation/response_types.py
keystone/api/validation/validators.py
keystone/application_credential/__init__.py
keystone/application_credential/core.py
keystone/application_credential/schema.py
keystone/application_credential/backends/__init__.py
keystone/application_credential/backends/base.py
keystone/application_credential/backends/sql.py
keystone/assignment/__init__.py
keystone/assignment/core.py
keystone/assignment/schema.py
keystone/assignment/backends/__init__.py
keystone/assignment/backends/base.py
keystone/assignment/backends/sql.py
keystone/assignment/role_backends/__init__.py
keystone/assignment/role_backends/base.py
keystone/assignment/role_backends/resource_options.py
keystone/assignment/role_backends/sql.py
keystone/assignment/role_backends/sql_model.py
keystone/auth/__init__.py
keystone/auth/core.py
keystone/auth/schema.py
keystone-28.0.0.dist-info/AUTHORS
keystone-28.0.0.dist-info/LICENSE
keystone-28.0.0.dist-info/METADATA
keystone-28.0.0.dist-info/WHEEL
keystone-28.0.0.dist-info/entry_points.txt
keystone-28.0.0.dist-info/pbr.json
keystone-28.0.0.dist-info/top_level.txt
keystone-28.0.0.dist-info/RECORD
